PyGestaltPlanner.cpython-310-darwin.so
gestalt_motion_planner.dylibs/libboost_serialization.dylib
gestalt_motion_planner.dylibs/libboost_filesystem.dylib
gestalt_motion_planner.dylibs/libboost_atomic.dylib
gestalt_motion_planner-0.1.20.dist-info/RECORD
gestalt_motion_planner-0.1.20.dist-info/WHEEL
gestalt_motion_planner-0.1.20.dist-info/METADATA
gestalt_motion_planner-0.1.20.dist-info/licenses/LICENSE
