Metadata-Version: 2.2
Name: gestalt-motion-planner
Version: 0.1.20
Summary: Trajectory Planner for Robotic Manipulators
Author: Mirko Kunze, Nina Grabka
